temp_manager/__init__.py
temp_manager/file_manager.py
temp_manager/folder_manager.py
temp_manager-0.0.3.dist-info/licenses/LICENSE
temp_manager-0.0.3.dist-info/METADATA
temp_manager-0.0.3.dist-info/WHEEL
temp_manager-0.0.3.dist-info/top_level.txt
temp_manager-0.0.3.dist-info/RECORD
