Metadata-Version: 2.4
Name: temp-manager
Version: 0.0.3
Summary: A package for managing temporary storage of files and folders
Author-email: Ronald Grefhorst <ronald@rgde.be>
Project-URL: Homepage, https://github.com/Grefron/temp-manager
Project-URL: Issues, https://github.com/Grefron/temp-manager/issues
Classifier: Programming Language :: Python :: 3
Classifier: License :: OSI Approved :: MIT License
Classifier: Operating System :: OS Independent
Requires-Python: >=3.8
License-File: LICENSE
Requires-Dist: watchdog
Requires-Dist: peewee
Dynamic: license-file
